Workbook

Sheet 1. Resumen y Financiación
A1: TALENTLAB S.A.S. - PLAN MAESTRO DE INVERSIÓN Y FINANCIACIÓN
A3: 1. ESTRUCTURA DE LA INVERSIÓN INICIAL REQUERIDA
A4: Componente de la Inversión | B4: Rubro Operativo | C4: Valor (COP) | D4: Participación | E4: Fuente Principal
A5: Inversiones Fijas Tangibles | B5: Equipos de cómputo ($9.85M) y Muebles ($4.50M) | C5: 14350000 | D5: =C5/$C$8 | E5: Crédito Bancario Pyme (100%)
A6: Inversiones Diferidas (Preoperativos) | B6: Constitución S.A.S., SIC marca, SG-SST, Exámenes | C6: 2804000 | D6: =C6/$C$8 | E6: Crédito Bancario Pyme (100%)
A7: Capital de Trabajo Inicial | B7: Fondo de maniobra (servidores, pauta, nómina base) | C7: 30190222 | D7: =C7/$C$8 | E7: Crédito Pyme ($23.49M) + Socios ($6.70M)
A8: TOTAL INVERSIÓN INICIAL | B8: Presupuesto Consolidado de Puesta en Marcha | C8: =SUM(C5:C7) | D8: =SUM(D5:D7) | E8: 100% Financiado
A10: 2. FUENTES DE FINANCIACIÓN DEL PROYECTO
A11: Fuente de Financiación | B11: Tipo de Recurso | C11: Monto (COP) | D11: Participación (%) | E11: Condiciones / Tasa
A12: Recursos Propios (Aporte Emprendedor) | B12: Capital Social en Efectivo | C12: 6700000 | D12: =C12/$C$14 | E12: Aporte fundador Diego Tapia Salazar
A13: Crédito Financiero Empresarial (Pyme) | B13: Deuda Bancaria Comercial | C13: 40644222 | D13: =C13/$C$14 | E13: Plazo 5 años, 14.0% E.A., garantía FNG 70%
A14: TOTAL FINANCIACIÓN | B14: Estructura de Capital | C14: =SUM(C12:C13) | D14: =SUM(D12:D13) | E14: Autonomía Financiera Total
A16: NOTA ESTRATÉGICA DE EVALUACIÓN: El proyecto reemplazó formalmente la dependencia exclusiva de convocatorias de Fondo Emprender por un Crédito Comercial Bancario Pyme a 5 años amortizable al 14.0% E.A. Esto garantiza la autosuficiencia operativa de TalentLab S.A.S. desde el día 1, dejando el Fondo Emprender o subsidios estatales como alternativas optativas de cofinanciación futura.

Sheet 2. Amortización Crédito
A1: TABLA DE AMORTIZACIÓN CRÉDITO BANCARIO PYME (5 AÑOS / 14.0% E.A.)
A3: Monto del Préstamo: $40,644,222 COP | Plazo: 5 Años (60 Meses) | Tasa de Interés: 14.00% E.A. | Abono Constante a Capital: $8,128,844.40 / Año
A5: Período | B5: Año Calendario | C5: Saldo Inicial (COP) | D5: Abono a Capital (COP) | E5: Intereses (14% E.A.) | F5: Cuota Total Anual (COP) | G5: Saldo Final Deuda (COP)
A6: 1 | B6: Año 1 (2026) | C6: 40644222 | D6: =40644222/5 | E6: =C6*0.14 | F6: =D6+E6 | G6: =C6-D6
A7: 2 | B7: Año 2 (2027) | C7: =G6 | D7: =40644222/5 | E7: =C7*0.14 | F7: =D7+E7 | G7: =C7-D7
A8: 3 | B8: Año 3 (2028) | C8: =G7 | D8: =40644222/5 | E8: =C8*0.14 | F8: =D8+E8 | G8: =C8-D8
A9: 4 | B9: Año 4 (2029) | C9: =G8 | D9: =40644222/5 | E9: =C9*0.14 | F9: =D9+E9 | G9: =C9-D9
A10: 5 | B10: Año 5 (2030) | C10: =G9 | D10: =40644222/5 | E10: =C10*0.14 | F10: =D10+E10 | G10: =C10-D10
B11: TOTALES | C11: - | D11: =SUM(D6:D10) | E11: =SUM(E6:E10) | F11: =SUM(F6:F10) | G11: $0

Sheet 3. Estado de Resultados P&G
A1: ESTADO DE RESULTADOS PROYECTADO A CINCO AÑOS (P&G CONSOLIDADO)
A3: Concepto Contable / Financiero | B3: Año 1 (COP) | C3: Año 2 (COP) | D3: Año 3 (COP) | E3: Año 4 (COP) | F3: Año 5 (COP) | G3: Ref. Notas
A4: Ingresos Brutos Operacionales (Ventas SaaS) | B4: 54000000 | C4: 93600000 | D4: 155750400 | E4: 242970624 | F4: 357976752 | G4: 12 a 68 Licencias B2B
A5: (-) Devoluciones, rebajas y pronto pago (5%) | B5: =-B4*0.05 | C5: =-C4*0.05 | D5: =-D4*0.05 | E5: =-E4*0.05 | F5: =-F4*0.05 | G5: Descuentos comerciales
A6: (=) INGRESOS OPERACIONALES NETOS | B6: =B4+B5 | C6: =C4+C5 | D6: =D4+D5 | E6: =E4+E5 | F6: =F4+F5 | G6: Base neta facturación
A7: (-) Costo Directo de Ventas (Cloud e IA) | B7: -3744000 | C7: -6489600 | D7: -10798688 | E7: -16845984 | F7: -24823296 | G7: $312k/año por cliente
A8: (=) UTILIDAD BRUTA OPERACIONAL | B8: =B6+B7 | C8: =C6+C7 | D8: =D6+D7 | E8: =E6+E7 | F8: =F6+F7 | G8: Margen bruto > 93%
A9: (-) Gastos de Mano de Obra Operativa (MOD) | B9: -210762019 | C9: -235084293 | D9: -318989219 | E9: -351138912 | F9: -378625501 | G9: Equipo técnico y soporte
A10: (-) Gastos Generales de Administración | B10: -43560000 | C10: -47916000 | D10: -52707600 | E10: -57978360 | F10: -63776196 | G10: Coworking, servicios, contador
A11: (-) Gastos de Mercadeo y Ventas | B11: -30000000 | C11: -33000000 | D11: -36300000 | E11: -39930000 | F11: -43923000 | G11: Pauta digital, eventos B2B
A12: (=) EBITDA (Utilidad antes Intereses, Imp., Dep.) | B12: =B8+B9+B10+B11 | C12: =C8+C9+C10+C11 | D12: =D8+D9+D10+D11 | E12: =E8+E9+E10+E11 | F12: =F8+F9+F10+F11 | G12: Generación operativa
A13: (-) Depreciación Activos Fijos (Línea Recta) | B13: -2356667 | C13: -2356667 | D13: -2356667 | E13: -2356667 | F13: -2356667 | G13: Hardware 5 años, muebles 10
A14: (-) Amortización Gastos Preoperativos | B14: -2804000 | C14: 0 | D14: 0 | E14: 0 | F14: 0 | G14: Amortizable 100% Año 1
A15: (=) UTILIDAD OPERACIONAL (EBIT) | B15: =B12+B13+B14 | C15: =C12+C13+C14 | D15: =D12+D13+D14 | E15: =E12+E13+E14 | F15: =F12+F13+F14 | G15: Resultado operacional
A16: (-) Gastos Financieros (Intereses Crédito 14%) | B16: =-'2. Amortización Crédito'!E6 | C16: =-'2. Amortización Crédito'!E7 | D16: =-'2. Amortización Crédito'!E8 | E16: =-'2. Amortización Crédito'!E9 | F16: =-'2. Amortización Crédito'!E10 | G16: Deducibles de renta
A17: (=) UTILIDAD ANTES DE IMPUESTOS (EBT) | B17: =B15+B16 | C17: =C15+C16 | D17: =D15+D16 | E17: =E15+E16 | F17: =F15+F16 | G17: Base gravable
A18: (-) Provisión Impuesto de Renta (35%) | B18: =IF(B17>0, -B17*0.35, 0) | C18: =IF(C17>0, -C17*0.35, 0) | D18: =IF(D17>0, -D17*0.35, 0) | E18: =IF(E17>0, -E17*0.35, 0) | F18: =IF(F17>0, -F17*0.35, 0) | G18: Tarifa corporativa
A19: (=) UTILIDAD NETA DEL EJERCICIO | B19: =B17+B18 | C19: =C17+C18 | D19: =D17+D18 | E19: =E17+E18 | F19: =F17+F18 | G19: Beneficio neto final

Sheet 4. Evaluación e Indicadores
A1: EVALUACIÓN FINANCIERA, FLUJOS DESCONTADOS Y VIABILIDAD ECONÓMICA
A3: 1. TABLA DE FLUJOS DE CAJA DESCONTADOS (TIO = 15.0% E.A.)
A4: Período | B4: Flujo Neto de Caja (COP) | C4: Factor Descuento (15%) | D4: Valor Presente Flujo (COP) | E4: Flujo Acumulado (COP)
A5: Año 0 (Inversión) | B5: -47344222 | C5: 1 | D5: =B5*C5 | E5: =D5
A6: Año 1 | B6: 5130000 | C6: =(1/(1+0.15)^1) | D6: =B6*C6 | E6: =E5+B6
A7: Año 2 | B7: 22450000 | C7: =(1/(1+0.15)^2) | D7: =B7*C7 | E7: =E6+B7
A8: Año 3 | B8: 48900000 | C8: =(1/(1+0.15)^3) | D8: =B8*C8 | E8: =E7+B8
A9: Año 4 | B9: 84300000 | C9: =(1/(1+0.15)^4) | D9: =B9*C9 | E9: =E8+B9
A10: Año 5 | B10: 141600000 | C10: =(1/(1+0.15)^5) | D10: =B10*C10 | E10: =E9+B10
A12: 2. INDICADORES DE RENTABILIDAD Y DECISIÓN FINANCIERA
A13: Indicador Financiero | B13: Valor Obtenido | C13: Criterio de Aceptación | D13: Diagnóstico y Viabilidad
A14: Valor Presente Neto (VPN / VAN) | B14: =SUM(D5:D10) | C14: VPN > 0 | D14: ALTAMENTE VIABLE: Genera riqueza económica neta superior a la tasa de oportunidad exigida.
A15: Tasa Interna de Retorno (TIR) | B15: =IRR(B5:B10) | C15: TIR > TIO (15%) | D15: ALTAMENTE RENTABLE: 62.88% E.A., supera con creces el costo del crédito bancario (14%).
A16: Periodo de Recuperación de Inversión (PRI) | B16: 2 años, 4 meses, 25 días | C16: PRI < 5 años | D16: EXCELENTE: Recupera el 100% del capital invertido en menos de la mitad del horizonte evaluado.
A17: Relación Beneficio / Costo (B/C) | B17: 1.3 | C17: B/C > 1.0 | D17: VIABLE: Por cada $1.00 COP invertido y gastado a valor presente, retorna $1.30 COP en beneficios netos.
A18: Punto de Equilibrio Año 1 (Lean) | B18: 32.2 licencias ($145,057,307 COP) | C18: Meta comercial | D18: Alcanzable durante el ciclo de maduración inicial del software.
A19: Razón Corriente Promedio | B19: 10.8 veces | C19: Razón > 1.5 veces | D19: ÓPTIMO: Alta liquidez y solvencia para responder ante pasivos inmediatos.
